smart_meeting_agent/__init__.py
smart_meeting_agent/__main__.py
smart_meeting_agent-0.2.3.dist-info/METADATA
smart_meeting_agent-0.2.3.dist-info/WHEEL
smart_meeting_agent-0.2.3.dist-info/entry_points.txt
smart_meeting_agent-0.2.3.dist-info/top_level.txt
smart_meeting_agent-0.2.3.dist-info/RECORD
