Metadata-Version: 2.4
Name: smart-meeting-agent
Version: 0.2.3
Summary:  
Author: rhythmli
Author-email: rhythmli.scu@gmail.com
Classifier: Programming Language :: Python :: 3
Classifier: Topic :: Software Development :: Libraries :: Python Modules
Classifier: Intended Audience :: Developers
Requires-Python: >=3.7
Requires-Dist: mcp>=1.6.0
Requires-Dist: requests
Dynamic: author
Dynamic: author-email
Dynamic: classifier
Dynamic: description
Dynamic: description-content-type
Dynamic: requires-dist
Dynamic: requires-python
Dynamic: summary
